lifeeasy/__init__.py
lifeeasy-2.3.3.dist-info/LICENSE
lifeeasy-2.3.3.dist-info/METADATA
lifeeasy-2.3.3.dist-info/WHEEL
lifeeasy-2.3.3.dist-info/top_level.txt
lifeeasy-2.3.3.dist-info/RECORD
