Metadata-Version: 2.1
Name: lifeeasy
Version: 2.3.3
Summary: A simple python toolbox.
Home-page: https://github.com/Animenosekai/lifeeasy
Author: Anime no Sekai
Author-email: niichannomail@gmail.com
License: MIT
Download-URL: https://github.com/Animenosekai/lifeeasy/archive/v1.6.tar.gz
Keywords: tools,one-line,easy,lifeeasy,library,toolbox,developer
Platform: UNKNOWN
Classifier: Development Status :: 4 - Beta
Classifier: Intended Audience :: Developers
Classifier: License :: OSI Approved :: MIT License
Classifier: Programming Language :: Python :: 3
Classifier: Programming Language :: Python :: 3.4
Classifier: Programming Language :: Python :: 3.5
Classifier: Programming Language :: Python :: 3.6
Classifier: Programming Language :: Python :: 3.7
Classifier: Programming Language :: Python :: 3.8
Classifier: Topic :: Software Development :: Build Tools
Requires-Dist: requests
Requires-Dist: psutil
Requires-Dist: imagehash
Requires-Dist: Pillow
Requires-Dist: numpy
